erisml/__init__.py
erisml/__version__.py
erisml/core/engine.py
erisml/core/model.py
erisml/core/norms.py
erisml/core/types.py
erisml/ethics/__init__.py
erisml/ethics/facts.py
erisml/ethics/judgement.py
erisml/ethics/profile_v02.py
erisml/ethics/profile_v03.py
erisml/ethics/domain/em_profile.py
erisml/ethics/domain/interfaces.py
erisml/ethics/governance/__init__.py
erisml/ethics/governance/aggregation.py
erisml/ethics/governance/config.py
erisml/ethics/interop/json_schema.py
erisml/ethics/interop/mcp_deme_server.py
erisml/ethics/interop/profile_adapters.py
erisml/ethics/interop/serialization.py
erisml/ethics/modules/__init__.py
erisml/ethics/modules/base.py
erisml/ethics/modules/geneva_base_em.py
erisml/ethics/modules/greek_tragedy_tragic_conflict_em.py
erisml/ethics/modules/triage_em.py
erisml/examples/bond_index_calibration_deme_fuzzing.py
erisml/examples/bond_index_calibration_deme_fuzzing_v3.py
erisml/examples/bond_index_calibration_deme_fuzzing_v4.py
erisml/examples/bond_index_calibration_test_suite.py
erisml/examples/bond_index_llm_evaluation.py
erisml/examples/bond_invariance_demo.orig2.py
erisml/examples/bond_invariance_demo.py
erisml/examples/greek_tragedy_pantheon_demo.py
erisml/examples/hello_deme.py
erisml/examples/tiny_home.py
erisml/examples/triage_ethics_demo.py
erisml/examples/triage_ethics_provenance_demo.py
erisml/examples/llm-eval/itai_bond_index_evaluation.py
erisml/interop/pddl_adapter.py
erisml/interop/pettingzoo_adapter.py
erisml/language/ast.py
erisml/language/parser.py
erisml/metrics/telemetry.py
erisml_apramey_test-0.1.2.dist-info/licenses/LICENSE.txt
erisml_apramey_test-0.1.2.dist-info/METADATA
erisml_apramey_test-0.1.2.dist-info/WHEEL
erisml_apramey_test-0.1.2.dist-info/top_level.txt
erisml_apramey_test-0.1.2.dist-info/RECORD
