Metadata-Version: 2.4
Name: erisml-apramey-test
Version: 0.1.2
Summary: ErisML Test Package
Author-email: "Andrew H. Bond" <andrew.bond@sjsu.edu>
License: AGI-HPC RESPONSIBLE AI LICENSE
Requires-Python: >=3.10
License-File: LICENSE.txt
Requires-Dist: numpy
Requires-Dist: scipy
Requires-Dist: pydantic
Requires-Dist: lark
Requires-Dist: pettingzoo
Dynamic: license-file
